napari_workflow_optimizer/__init__.py
napari_workflow_optimizer/_optimizer.py
napari_workflow_optimizer/_tests/__init__.py
napari_workflow_optimizer/_tests/test_dock_widget.py
napari_workflow_optimizer/_tests/test_optimizers.py
napari_workflow_optimizer/_tests/test_plotter.py
napari_workflow_optimizer/gui/__init__.py
napari_workflow_optimizer/gui/_dock_widget.py
napari_workflow_optimizer/gui/_plotter.py
napari_workflow_optimizer-0.1.4.dist-info/LICENSE
napari_workflow_optimizer-0.1.4.dist-info/METADATA
napari_workflow_optimizer-0.1.4.dist-info/WHEEL
napari_workflow_optimizer-0.1.4.dist-info/entry_points.txt
napari_workflow_optimizer-0.1.4.dist-info/top_level.txt
napari_workflow_optimizer-0.1.4.dist-info/RECORD
