Metadata-Version: 2.1
Name: napari-workflow-optimizer
Version: 0.1.4
Summary: Optimize image processing workflows in napari for segmentation quality
Home-page: https://github.com/haesleinhuepf/napari-workflow-optimizer
Author: Robert Haase
Author-email: robert.haase@tu-dresden.de
License: BSD-3-Clause
Project-URL: Bug Tracker, https://github.com/haesleinhuepf/napari-workflow-optimizer/issues
Project-URL: Documentation, https://github.com/haesleinhuepf/napari-workflow-optimizer#README.md
Project-URL: Source Code, https://github.com/haesleinhuepf/napari-workflow-optimizer
Project-URL: User Support, https://github.com/haesleinhuepf/napari-workflow-optimizer/issues
Platform: UNKNOWN
Classifier: Development Status :: 3 - Alpha
Classifier: Intended Audience :: Science/Research
Classifier: Framework :: napari
Classifier: Topic :: Scientific/Engineering :: Image Processing
Classifier: Topic :: Scientific/Engineering :: Information Analysis
Classifier: Programming Language :: Python
Classifier: Programming Language :: Python :: 3
Classifier: Programming Language :: Python :: 3.7
Classifier: Programming Language :: Python :: 3.8
Classifier: Programming Language :: Python :: 3.9
Classifier: Operating System :: OS Independent
Classifier: License :: OSI Approved :: BSD License
Requires-Python: >=3.7
License-File: LICENSE
Requires-Dist: napari-plugin-engine (>=0.1.4)
Requires-Dist: numpy
Requires-Dist: pyclesperanto-prototype
Requires-Dist: scikit-learn
Requires-Dist: napari-time-slicer
Requires-Dist: matplotlib
Requires-Dist: scipy
Requires-Dist: napari-workflows
Requires-Dist: napari-assistant (>=0.1.9)
